<?xml version="1.0" encoding="iso-8859-1"?>
<data>

	<slide>
		<element type="IMAGE" x="0" y="0" width="470" height="400" src="1.1.2.4.jpg" />
		<element type="IMAGE" x="296.75" y="86.2" width="107" height="58" src="1_1_2_4A.jpg" subType="STD"/>
		<element type="IMAGE" x="296.75" y="213.95" width="107" height="58" src="1_1_2_4B.jpg" subType="STD"/>
		<element type="TEXT" compId="ID_txt02" x="271" y="152" width="158.8" expand="down" align="center" />
		<element type="TEXT" compId="ID_txt03" x="272" y="181" width="158.05" expand="left+right" align="center" />
		<element type="TEXT" compId="ID_txt04" x="271" y="280" width="158.8" expand="down" align="center" />
		<element type="TEXT" compId="ID_txt01" x="128" y="221" width="67.15" expand="down" align="center" />
		<element type="TEXT" subType="TITLE" compId="ID_title"/>
	</slide>


</data>