<?xml version="1.0" encoding="iso-8859-1"?>
<data>
<slide type="MBAR" width="780">
	<slide>
		<element type="IMAGE" src="media_8.1.1.9.jpg" width="780" height="400" x="0" y="0" />
		<element type="TEXT" compId="ID_s1_txt01" x="286.95" y="24.95" width="88.65" expand="up+down" align="center" color="#ffffff"/>
		<element type="TEXT" compId="ID_s1_txt02" x="375" y="24.95" width="121" expand="up+down" align="center" color="#ffffff"/>
		<element type="TEXT" compId="ID_s1_txt03" x="498.6" y="24.95" width="121" expand="up+down" align="center" color="#ffffff"/>
		<element type="TEXT" compId="ID_s1_txt04" x="621.25" y="24.95" width="121" expand="up+down" align="center" color="#ffffff"/>
		<element type="TEXT" compId="ID_s1_txt05" x="283.95" y="67.95" width="88.65" expand="up+down" align="center" />
		<element type="TEXT" compId="ID_s1_txt06" x="283.95" y="110.95" width="88.65" expand="up+down" align="center"/>
		<element type="TEXT" compId="ID_s1_txt07" x="283.95" y="153.95" width="88.65" expand="up+down" align="center"/>
		<element type="TEXT" compId="ID_s1_txt08" x="283.95" y="197.95" width="88.65" expand="up+down" align="center"/>
		<element type="TEXT" compId="ID_s1_txt09" x="283.95" y="239.95" width="88.65" expand="up+down" align="center"/>
		<element type="TEXT" compId="ID_s1_txt10" x="283.95" y="283.95" width="88.65" expand="up+down" align="center"/>
		<element type="TEXT" compId="ID_s1_txt11" x="283.95" y="326.95" width="88.65" expand="up+down" align="center"/>
		<element type="TEXT" compId="ID_s1_inst" x="1" y="1" width="273.3" expand="down" align="left"/>
		<element type="ACTIVITY" subType="DRAGDROP" method="NORMAL" replicate="true" compWidth="90" compHeight="35.95" dragIcon="" dropIcon="" tickPosition="left" dragAlpha="0.3">	
		
		<subelement type="DROP"  x="398.7" y="58.55" match="1"/>
		<subelement type="DROP"  x="398.7" y="101.65" match="7"/>
		<subelement type="DROP"  x="398.7" y="144.75" match="4"/>
		<subelement type="DROP"  x="398.7" y="187.85" match="7"/>
		<subelement type="DROP"  x="398.7" y="230.95" match="10"/>
		<subelement type="DROP"  x="398.7" y="274.05" match="13"/>
		<subelement type="DROP"  x="398.7" y="317.15" match="2"/>
		
		<subelement type="DROP"  x="521.9" y="58.55" match="11"/>
		<subelement type="DROP"  x="521.9" y="101.65" match="14"/>
		<subelement type="DROP"  x="521.9" y="144.75" match="11"/>
		<subelement type="DROP"  x="521.9" y="187.85" match="11"/>
		<subelement type="DROP"  x="521.9" y="230.95" match="5"/>
		<subelement type="DROP"  x="521.9" y="274.05" match="14"/>
		<subelement type="DROP"  x="521.9" y="317.15" match="8"/>
		
		<subelement type="DROP"  x="644.6" y="58.55" match="0"/>
		<subelement type="DROP"  x="644.6" y="101.65" match="0"/>
		<subelement type="DROP"  x="644.6" y="144.75" match="0"/>
		<subelement type="DROP"  x="644.6" y="187.85" match="3"/>
		<subelement type="DROP"  x="644.6" y="230.95" match="9"/>
		<subelement type="DROP"  x="644.6" y="274.05" match="6"/>
		<subelement type="DROP"  x="644.6" y="317.15" match="12"/>
		
		
		<subelement type="DRAG" compId="ID_s1_txt19" x="2.1" y="157.85" /><!--NO 0-->
		<subelement type="DRAG" compId="ID_s1_txt28" x="95" y="157.85" /><!--2mbps 1-->
		<subelement type="DRAG" compId="ID_s1_txt23" x="188.05" y="157.85" /><!--1.7 2-->
				
		<subelement type="DRAG" compId="ID_s1_txt18" x="2.1" y="197.65" /><!--802.11b 3-->
		<subelement type="DRAG" compId="ID_s1_txt16" x="95" y="197.65" /><!--11Mbps 4-->
		<subelement type="DRAG" compId="ID_s1_txt25" x="188.05" y="197.65" /><!--2.4 and 5 5-->
				
		<subelement type="DRAG" compId="ID_s1_txt27" x="2.1" y="237.45" /><!--802.11a/n 6-->
		<subelement type="DRAG" compId="ID_s1_txt15" x="95" y="237.45" /><!--54mbps 7-->
		<subelement type="DRAG"  compId="ID_s1_txt21" x="188.05" y="237.45" /><!--2.4,5,60 8-->
		
		<subelement type="DRAG"  compId="ID_s1_txt20" x="2.1" y="277.25" /><!--802.11a/b/g 9-->
		<subelement type="DRAG"  compId="ID_s1_txt22" x="95" y="277.25" /><!--600 10-->
		<subelement type="DRAG" compId="ID_s1_txt17" x="188.05" y="277.25" /><!--2.4 Ghz 11-->
		
		<subelement type="DRAG" compId="ID_s1_txt14" x="2.1" y="317.05" /><!--802.11a/b/n/ac 12-->
		<subelement type="DRAG"  compId="ID_s1_txt26" x="95" y="317.05" /><!--1.3 13 -->
		<subelement type="DRAG" compId="ID_s1_txt24" x="188.05" y="317.05" /><!--5GHz 14-->
		
		

			
		<subelement type="CHECK" x="480" y="366" width="120" height="21" compId="ID_s1_CHECK"/>
		<subelement type="RESET" x="632" y="366" width="110" height="21" compId="ID_s1_RESET"/>
		<subelement type="FEEDBACK" x="44" y="127.9" width="200" height="125" correctTitleId="ID_s1_CORRECT_TITLE" correctBodyId=        "ID_s1_CORRECT_BODY" wrongTitleId="ID_s1_INCORRECT_TITLE" wrongBodyId="ID_s1_INCORRECT_BODY"/>
	  </element>   
	</slide>
	<slide>
			<element type="TEXT" compId="ID_s2_inst" x="1" y="1" width="301.4" expand="down" align="left" />
			<element type="TEXT" compId="ID_s2_text01" x="311" y="15" width="432.1" expand="up+down" align="center" color="#e6360" />
			<element type="TEXT" compId="ID_s2_txt02" x="312" y="58" width="139.7" expand="up+down" align="center" color="#ffffff" />
			<element type="TEXT" compId="ID_r1_c1" x="312" y="99" width="98.5" expand="up+down" align="left" />
			<element type="TEXT" compId="ID_s2_txt03" x="457" y="58" width="139.7" expand="up+down" align="center" color="#ffffff" />
			<element type="TEXT" compId="ID_s2_txt04" x="601" y="58" width="139.7" expand="up+down" align="center" color="#ffffff" />
			<element type="TEXT" compId="ID_r2_c1" x="312" y="143" width="98.5" expand="up+down" align="left" />
			<element type="TEXT" compId="ID_r3_c1" x="312" y="187" width="98.5" expand="up+down" align="left" />
			<element type="TEXT" compId="ID_r4_c1" x="312" y="231" width="98.5" expand="up+down" align="left" />
			<element type="TEXT" compId="ID_r1_c2" x="457" y="99" width="98.5" expand="up+down" align="left" />
			<element type="TEXT" compId="ID_r2_c2" x="457" y="143" width="98.5" expand="up+down" align="left" />
			<element type="TEXT" compId="ID_r3_c2" x="457" y="187" width="98.5" expand="up+down" align="left" />
			<element type="TEXT" compId="ID_r4_c2" x="457" y="231" width="98.5" expand="up+down" align="left" />
			<element type="TEXT" compId="ID_r5_c2" x="457" y="275" width="98.5" expand="up+down" align="left" />
			<element type="TEXT" compId="ID_r6_c2" x="457" y="319" width="98.5" expand="up+down" align="left" />
			<element type="TEXT" compId="ID_r1_c3" x="601" y="99" width="98.5" expand="up+down" align="left" />
			<element type="TEXT" compId="ID_r2_c3" x="601" y="143" width="98.5" expand="up+down" align="left" />
			<element type="TEXT" compId="ID_r3_c3" x="601" y="187" width="98.5" expand="up+down" align="left" />
			<element type="TEXT" compId="ID_r4_c3" x="601" y="231" width="98.5" expand="up+down" align="left" />
			<element type="TEXT" compId="ID_r5_c3" x="601" y="275" width="98.5" expand="up+down" align="left" />
			<element type="TEXT" compId="ID_r6_c3" x="601" y="319" width="98.5" expand="up+down" align="left" />
			<element type="TEXT" compId="" x="312" y="275" width="98.5" expand="right" align="left" />
			<element type="TEXT" compId="" x="312" y="319" width="98.5" expand="right" align="left" />
			<element type="IMAGE" src="media_8.1.1.9A.jpg" width="780" height="400" x="0" y="0" />
			<element type="ACTIVITY" subType="DRAGDROP" method="NORMAL" replicate="true" compWidth="40" compHeight="40" dragIcon="../../../common/images/html/tickDragIcon.png" dropIcon="" tickPosition="left" dragAlpha="0.3">
			
			<subelement type="DROP"  x="412" y="87" match="null"/>
			<subelement type="DROP"  x="412" y="219" match="0"/>
			<subelement type="DROP"  x="412" y="131" match="0"/>
			<subelement type="DROP"  x="412" y="175" match="0"/>
			<subelement type="DROP"  x="412" y="263" match="null"/>
			<subelement type="DROP"  x="412" y="307" match="0"/>
			<subelement type="DROP"  x="557" y="87" match="0"/>
			<subelement type="DROP"  x="557" y="219" match="0"/>
			<subelement type="DROP"  x="557" y="131" match="null"/>
			<subelement type="DROP"  x="557" y="175" match="null"/>
			<subelement type="DROP"  x="557" y="263" match="0"/>
			<subelement type="DROP"  x="557" y="307" match="0"/>
			<subelement type="DROP"  x="701" y="87" match="null"/>
			<subelement type="DROP"  x="701" y="219" match="null"/>
			<subelement type="DROP"  x="701" y="131" match="null"/>
			<subelement type="DROP"  x="701" y="175" match="null"/>
			<subelement type="DROP"  x="701" y="263" match="null"/>
			<subelement type="DROP"  x="701" y="307" match="0"/>
			<subelement type="DRAG"  x="243" y="175" match="null"/>
			
			<subelement type="CHECK" x="520" y="363.8" width="100" height="23" compId="ID_s2_check"/>
			<subelement type="RESET" x="645.1" y="363.8" width="100" height="23" compId="ID_s2_reset"/>
			<subelement type="FEEDBACK" x="51" y="224" width="200" height="125" correctTitleId="ID_s2_CORRECT_TITLE" correctBodyId="ID_s2_CORRECT_BODY" wrongTitleId="ID_s2_INCORRECT_TITLE" wrongBodyId="ID_s2_INCORRECT_BODY"/>
	 </element> 
	</slide>
	<slide>
		<element type="IMAGE" src="media_8.1.1.9B.jpg" x="0" y="0" width="780" height="400"/>
		<element type="ACTIVITY" subType="DRAGDROP" method="NORMAL" replicate="true" compWidth="150" compHeight="36" dragIcon="" dropIcon="" tickPosition="left" dragAlpha="0.3" matchType="group"  grouptype="multi">
		<subelement type="DROP"  x="591" y="190" group="c" empty="null" />
		<subelement type="DROP"  x="591" y="240" group="c"/>
		<subelement type="DROP"  x="591" y="290" group="c"/>
		
		<subelement type="DROP"  x="401" y="190" group="b"  />
		<subelement type="DROP"  x="401" y="240" group="b" />
		<subelement type="DROP"  x="401" y="290" group="b"/>
		
		
		<subelement type="DROP"  x="211" y="190" group="a"  />
		<subelement type="DROP"  x="211" y="240" group="a"/>
		<subelement type="DROP"  x="211" y="290" group="a"/>
		
		<subelement type="DRAG" compId="ID_s3_drag01" x="10" y="111" group="c,b"/><!--radio-->
		<subelement type="DRAG" compId="ID_s3_drag02" x="10" y="152" group="b"/><!--sattellite-->
		<subelement type="DRAG" compId="ID_s3_drag03" x="10" y="193" group="a"/><!--bluetooth-->
		<subelement type="DRAG" compId="ID_s3_drag04" x="10" y="233" group="c"/><!--radar landing-->
		<subelement type="DRAG" compId="ID_s3_drag05" x="10" y="274" group="a"/><!--cellular-->
		<subelement type="DRAG" compId="ID_s3_drag06" x="10" y="314" group="b"/><!--microwave-->
		<subelement type="DRAG" compId="ID_s3_drag07" x="10" y="355" group="a"/><!--GPS-->
		
		<element type="TEXT" compId="ID_s3_inst" x="5" y="1" width="743.55" expand="down" align="left"/>
		<element type="TEXT" compId="ID_s3_header01" x="195" y="153" width="165.8" expand="down" align="center" />
		<element type="TEXT" compId="ID_s3_header02" x="385" y="153" width="165.8" expand="down" align="center"/>
		<element type="TEXT" compId="ID_s3_header03" x="575" y="153" width="165.8" expand="down" align="center"/>
		<element type="TEXT" compId="ID_s3_tableTitle" x="195" y="131" width="547.6" expand="up" align="center" size="13"/>
		<subelement type="CHECK" x="520" y="368" width="100" height="21" compId="ID_s3_check"/>
		<subelement type="RESET" x="645" y="368" width="100" height="21" compId="ID_s3_reset"/>
		<subelement type="FEEDBACK" x="367" y="15" width="201.05" height="125" correctTitleId="ID_s3_CORRECT_TITLE" correctBodyId=        "ID_s3_CORRECT_BODY" wrongTitleId="ID_s3_INCORRECT_TITLE" wrongBodyId="ID_s3_INCORRECT_BODY"/>
	  </element>   
		</slide>
</slide>
</data>