<?xml version="1.0" encoding="iso-8859-1"?>
<data>
<slide>
			<element type="IMAGE" subType="STD" src="1_1_1_7A.jpg" x="9" y="33" width="150.25" height="118"/>
			<element type="IMAGE" subType="STD" src="1_1_1_7B.jpg" x="180.95" y="33" width="124" height="124"/>
			<element type="IMAGE" subType="STD" src="1_1_1_7C.jpg" x="344.75" y="33" width="108.1" height="102"/>
			<element type="IMAGE" subType="STD" src="1_1_1_7D.jpg" x="4.05" y="189" width="158.05" height="105.55"/>
			<element type="IMAGE" subType="STD" src="1_1_1_7E.jpg" x="189.3" y="189" width="168.65" height="111.35"/>
			<element type="IMAGE" subType="STD" src="1_1_1_7F.jpg" x="379.25" y="189" width="72" height="179"/>
			
			<element type="TEXT" compId="ID_txt01" width="150.25" x="9" y="15" align="center" expand="up" />
			<element type="TEXT" compId="ID_txt02" width="124" x="180" y="15" align="center" expand="up" />
			<element type="TEXT" compId="ID_txt03" width="133" x="330.95" y="15" align="center" expand="up" />
			<element type="TEXT" compId="ID_txt04" width="158.05" x="12.05" y="171" align="center" expand="up" />
			<element type="TEXT" compId="ID_txt05" width="172.95" x="180.3" y="171" align="center" expand="up" />
			<element type="TEXT" compId="ID_txt06" width="95.95" x="363.95" y="171" align="center" expand="up" />
			<element type="TEXT" compId="ID_txt07" width="354.8" x="10.05" y="314" align="left" expand="down" />
</slide>

</data>