<?xml version="1.0" encoding="iso-8859-1"?>
<data>
	<slide width="780">
		<element type="IMAGE" x="30" y="92" width="238" height="285" src="bg1.png" />
		<element type="IMAGE" x="331" y="42" width="410.6" height="314.95" src="bg.png" />
		<element type="TEXT" compId="ID_inst" x="2" y="1" width="293.4" expand="down" align="left" />
		<element type="TEXT" compId="ID_header01" x="336" y="50" width="104.5" expand="up+down" align="center" />
		<element type="TEXT" compId="ID_header02" x="469" y="50" width="104.5" expand="up+down" align="center" />
		<element type="TEXT" compId="ID_header03" x="603" y="50" width="104.5" expand="up+down" align="center" />
		<element type="TEXT" compId="ID_drop_header" x="310" y="25" width="433.95" expand="up" align="center" />
		<element type="TEXT" compId="ID_drag_header" x="39.35" y="76" width="232.95" expand="up" align="center" />
		
		<element type="ACTIVITY" subType="DRAGDROP" method="NORMAL" replicate="false" compWidth="100" compHeight="36" dragIcon="" dropIcon="" tickPosition="left" dragAlpha=".3" matchType="group">
		
			<subelement type="DRAG" compId="ID_a01_DS" x="40" y="105" group="a" />
			<subelement type="DRAG" compId="ID_a02_DS" x="40" y="163"  group="a"/>
			<subelement type="DRAG" compId="ID_a03_DS" x="40" y="221"  group="a"/>
			<subelement type="DRAG" compId="ID_a04_DS" x="161" y="105"  group="a"/>
			
			<subelement type="DRAG" compId="ID_b01_DS" x="161" y="163"  group="b"/>
			<subelement type="DRAG" compId="ID_b02_DS" x="161" y="221"  group="c"/>
			<subelement type="DRAG" compId="ID_b03_DS" x="40" y="336"  group="b"/>
			<subelement type="DRAG" compId="ID_b04_DS" x="161" y="278"  group="b"/>
			<subelement type="DRAG" compId="ID_b05_DS" x="161" y="336"  group="b"/>
			
			<subelement type="DRAG" compId="ID_c01_DS" x="40" y="278"  group="c"/>
			
			
			<subelement type="DROP" x="348" y="80"  group="a"/> <!-- 0 -->
			<subelement type="DROP" x="348" y="138"  group="a"/> <!-- 1 -->
			<subelement type="DROP" x="348" y="196" group="a"/> <!-- 2 -->
			<subelement type="DROP" x="348" y="251"  group="a"/> <!-- 3 -->
			<subelement type="DROP" x="348" y="311" group="a" empty="null" /> <!-- 4 -->
			
			<subelement type="DROP" x="481" y="80"  group="b"/> <!-- 5 -->
			<subelement type="DROP" x="481" y="138"  group="b"/> <!-- 6 -->
			<subelement type="DROP" x="481" y="196"  group="b"/> <!-- 7 -->
			<subelement type="DROP" x="481" y="251"  group="b"/> <!-- 8 -->
			<subelement type="DROP" x="481" y="311" group="b" empty="null"/> <!-- 9 -->
			
			<subelement type="DROP" x="614" y="80"   group="c"/> <!-- 10 -->
			<subelement type="DROP" x="614" y="138" group="c"/> <!-- 11 -->
			<subelement type="DROP" x="614" y="196" group="c" empty="null"/> <!-- 12 -->
			<subelement type="DROP" x="614" y="253" group="c" empty="null"/> <!-- 13 -->
			<subelement type="DROP" x="614" y="311" group="c" empty="null"/> <!-- 14 -->
			
			
			
			<subelement type="CHECK" x="510" y="370" width="90" height="21" compId="ID_CHECK"/>
		  <subelement type="RESET" x="625" y="370" width="90" height="21" compId="ID_RESET"/>
		  
		  <subelement type="FEEDBACK" x="50" y="200" width="200" height="125" correctTitleId="ID_s1_CORRECT_TITLE" correctBodyId="ID_s1_CORRECT_BODY" wrongTitleId="ID_s1_INCORRECT_TITLE" wrongBodyId="ID_s1_INCORRECT_BODY"/>
		  
		</element>
	</slide>
</data>