<?xml version="1.0" encoding="iso-8859-1"?>
<data>
	<slide type="MBAR">
	<!-- slide 01 -->
	<slide>
		<element type="IMAGE" x="0" y="20" width="440" height="370" src="media_6.2.2.2_A.png" />
		<element type="TEXT" compId="ID_s1_txt01" x="373" y="165" width="55.25" expand="up+down" align="center" />
		<element type="TEXT" compId="ID_s1_txt02" x="373" y="300" width="55.25" expand="up+down" align="center" />
		<element type="TEXT" compId="ID_s1_txt03" x="275" y="73" width="70" expand="up+down" align="center" />
		<element type="TEXT" compId="ID_s1_txt04" x="274" y="165" width="80" expand="up+down" align="center"  />
		<element type="TEXT" compId="ID_s1_txt05" x="280" y="240" width="68.25" expand="down" align="center" />
		<element type="TEXT" compId="ID_s1_txt06" x="282" y="340" width="55.25" expand="down" align="center"  />
		<element type="TEXT" compId="ID_s1_txt07" x="138" y="62" width="55.25" expand="down" align="center" />
		<element type="TEXT" compId="ID_s1_txt08" x="129" y="187" width="59.8" expand="up+down" align="center" />
		<element type="TEXT" compId="ID_s1_txt09" x="39" y="208" width="75" expand="right+down" align="left"  />
		<element type="TEXT" compId="ID_s1_txt10" x="13" y="335" width="233.55" expand="left+right" align="center"  />
		<element type="TEXT" subType="TITLE" compId="ID_s1_title"/>
	</slide>

	<!-- slide 02 -->
	<slide>
		<element type="TEXT" compId="ID_s2_txt01" x="4" y="183" width="170" expand="down" align="center" />
		<element type="TEXT" compId="ID_s2_txt02" x="248" y="179" width="170" expand="down" align="center" />
		<element type="TEXT" compId="ID_s2_txt03" x="138" y="367" width="180" expand="down" align="center" />
		<element type="IMAGE" x="257" y="31" width="170" height="136" subType="STD" src="6_2_2_2_A.jpg" />
		<element type="IMAGE" x="13" y="33" width="170" height="136" subType="STD" src="6_2_2_2_B.jpg" />
		<element type="IMAGE" x="144" y="220" width="170" height="136" subType="STD" src="6_2_2_2_C.jpg" />
		<element type="TEXT" subType="TITLE" compId="ID_s2_title"/>
	</slide>
	</slide>

</data>