<?xml version="1.0" encoding="utf-8"?>
<data>
	<slide  width="780" type="MBAR"> <!--Slide 01-->
	<slide>
		<element type="IMAGE" src="9.2.1.9.jpg" x="0" y="0" width="780" height="400"/>
		<element type="TEXT" id="ID_static_1" text="192.168.1.66" x="35.5" y="71.7" align="center" width="71.1" bold="1" />
		<element type="TEXT" id="ID_static_2" text="192.168.1.0/24" x="35.5" y="140.7" align="center" width="80.25" bold="1" />
		<element type="TEXT" id="ID_static_3" text="LAN1" x="56.05" y="156.25" align="center" width="35.75" bold="1" />
		<element type="TEXT" id="ID_static_4" text="Gi0/0" x="175" y="166.35" align="center" width="33.55" />
		<element type="TEXT" id="ID_static_5" text="Gi0/1" x="238.5" y="206.25" align="center" width="33.55" />
		<element type="TEXT" id="ID_static_6" text="192.168.2.0/24" x="236" y="242.55" align="center" width="80.25" bold="1" />
		<element type="TEXT" id="ID_static_7" text="LAN2" x="257.6" y="259.25" align="center" width="35.75" bold="1" />
		<element type="TEXT" id="ID_static_8" text="172.16.1.0/30" x="276" y="206.25" align="center" width="74.15" bold="1" />
		<element type="TEXT" id="ID_static_9" text="S0/0/0" x="302" y="166.35" align="center" width="39.15" />
		<element type="TEXT" id="ID_static_10" text="S0/0/0" x="393" y="171.05" align="center" width="39.15" />
		<element type="TEXT" id="ID_static_11" text="Gi0/1" x="422.55" y="210.75" align="center" width="33.55" />
		<element type="TEXT" id="ID_static_12" text="192.168.4.0/24" x="388.5" y="242.55" align="center" width="80.25" bold="1" />
		<element type="TEXT" id="ID_static_13" text="LAN4" x="410.1" y="259.25" align="center" width="35.75" bold="1" />
		<element type="TEXT" id="ID_static_14" text="Gi0/0" x="485.1" y="170.05" align="center" width="33.55" />
		<element type="TEXT" id="ID_static_15" text="192.168.3.0/24" x="528.55" y="184.75" align="center" width="80.25" bold="1" />
		<element type="TEXT" id="ID_static_16" text="LAN3" x="557.2" y="196.35" align="center" width="35.75" bold="1" />
		<element type="TEXT" id="ID_static_17" text="192.168.4.12" x="587.1" y="353.6" align="center" width="71.1" bold="1" />
		<element type="TEXT" id="ID_static_18" text="192.168.3.77" x="592.75" y="71.7" align="center" width="71.1" bold="1" />
		<element type="TEXT" compId="ID_s1_inst" x="2" y="1" width="699.4" expand="down" align="left" />
	</slide> <!--Slide 02-->
	<slide>
		<element type="TEXT" compId="ID_s2_inst" x="2" y="1" width="352.9" expand="down" align="left" size="11"/>
		<element type="TEXT" compId="ID_s2_target_header" x="393" y="31" width="180" expand="down" align="center" size="11"/>
		<element type="IMAGE" src="9.2.1.9_s2.jpg" x="0" y="0" width="780" height="400"/>

		<element type="ACTIVITY" subType="DRAGDROP" method="NORMAL" replicate="false" compWidth="170" compHeight="40" dragIcon="" dropIcon="" tickPosition="left" dragAlpha=".3">
		
			  <subelement type="DRAG" x="576.15" y="38.95" compId="ID_s2_drag01" />	
			  <subelement type="DRAG" x="576.15" y="85.25" compId="ID_s2_drag02" />
			  <subelement type="DRAG" x="576.15" y="131.55" compId="ID_s2_drag03" />
			  <subelement type="DRAG" x="576.15" y="177.85" compId="ID_s2_drag04" />
			  <subelement type="DRAG" x="576.15" y="224.15" compId="ID_s2_drag05" />
			  <subelement type="DRAG" x="576.15" y="270.45" compId="ID_s2_drag06" />
			  <subelement type="DRAG" x="576.15" y="317" compId="ID_s2_drag07" />
		 	 
		  
		 
	
			  <subelement type="DROP" x="398.1" y="85.25"  match="5" />
			  <subelement type="DROP" x="398.1" y="131.55"   match="2"/>
			  <subelement type="DROP" x="398.1" y="177.85"   match="6"/>
			  <subelement type="DROP" x="398.1" y="224.15"  match="3"/>
			  <subelement type="DROP" x="398.1" y="270.45"  match="1"/>
			  
		  
			  <subelement type="CHECK" x="505.25" y="377" width="100" height="23.3" compId="ID_s2_CHECK"/>
			  <subelement type="RESET" x="633" y="377" width="100" height="23.3" compId="ID_s2_RESET"/>
		  
			  <subelement type="FEEDBACK" x="59" y="170" width="240" height="180" correctTitleId="ID_s2_CORRECT_TITLE" correctBodyId="ID_s2_CORRECT_BODY" wrongTitleId="ID_s2_INCORRECT_TITLE" wrongBodyId="ID_s2_INCORRECT_BODY"/>
		
		  
		</element>  
	</slide> <!--Slide 03-->
	<slide>
		<element type="TEXT" compId="ID_s3_inst" x="2" y="1" width="363.75" expand="down" align="left" size="11"/>
		<element type="TEXT" compId="ID_s3_target_header" x="393" y="31" width="180" expand="down" align="center" size="11"/>
		<element type="IMAGE" src="9.2.1.9_s2.jpg" x="0" y="0" width="780" height="400"/>

		<element type="ACTIVITY" subType="DRAGDROP" method="NORMAL" replicate="false" compWidth="170" compHeight="40" dragIcon="" dropIcon="" tickPosition="left" dragAlpha=".3">
		
			  <subelement type="DRAG" x="577.15" y="44" compId="ID_s3_drag01" />	
			  <subelement type="DRAG" x="577.15" y="92.65" compId="ID_s3_drag02" />
			  <subelement type="DRAG" x="577.15" y="141.3" compId="ID_s3_drag03" />
			  <subelement type="DRAG" x="577.15" y="189.95" compId="ID_s3_drag04" />
			  <subelement type="DRAG" x="577.15" y="238.6" compId="ID_s3_drag05" />
			  <subelement type="DRAG" x="577.15" y="287.4" compId="ID_s3_drag06" />
		 	 
		  
		 
	
			  <subelement type="DROP" x="396.1" y="92.65"  match="0" />
			  <subelement type="DROP" x="396.1" y="141.3"   match="1"/>
			  <subelement type="DROP" x="396.1" y="189.95"   match="3"/>
			  <subelement type="DROP" x="396.1" y="238.6"  match="4"/>
			  
		  
			  <subelement type="CHECK" x="505.25" y="377" width="100" height="23.3" compId="ID_s3_CHECK"/>
			  <subelement type="RESET" x="633" y="377" width="100" height="23.3" compId="ID_s3_RESET"/>
		  
			  <subelement type="FEEDBACK" x="59" y="170" width="240" height="180" correctTitleId="ID_s3_CORRECT_TITLE" correctBodyId="ID_s3_CORRECT_BODY" wrongTitleId="ID_s3_INCORRECT_TITLE" wrongBodyId="ID_s3_INCORRECT_BODY"/>
		
		  
		</element>  
	</slide> <!--Slide 04-->
	<slide>
		<element type="TEXT" compId="ID_s4_inst" x="2" y="1" width="357.85" expand="down" align="left" size="11"/>
		<element type="TEXT" compId="ID_s4_target_header" x="393" y="31" width="180" expand="down" align="center" size="11"/>
		<element type="IMAGE" src="9.2.1.9_s2.jpg" x="0" y="0" width="780" height="400"/>

		<element type="ACTIVITY" subType="DRAGDROP" method="NORMAL" replicate="false" compWidth="170" compHeight="40" dragIcon="" dropIcon="" tickPosition="left" dragAlpha=".3">
		
			  <subelement type="DRAG" x="577.15" y="50" compId="ID_s4_drag01" />	
			  <subelement type="DRAG" x="577.15" y="97.25" compId="ID_s4_drag02" />
			  <subelement type="DRAG" x="577.15" y="144.5" compId="ID_s4_drag03" />
			  <subelement type="DRAG" x="577.15" y="191.75" compId="ID_s4_drag04" />
			  <subelement type="DRAG" x="577.15" y="239" compId="ID_s4_drag05" />
			  <subelement type="DRAG" x="577.15" y="286.4" compId="ID_s4_drag06" />
		 	 
		  
		 
	
			  <subelement type="DROP" x="396.1" y="97.25"  match="5" />
			  <subelement type="DROP" x="396.1" y="144.5"   match="3"/>
			  <subelement type="DROP" x="396.1" y="191.75"   match="1"/>
			  
		  
			  <subelement type="CHECK" x="505.25" y="377" width="100" height="23.3" compId="ID_s4_CHECK"/>
			  <subelement type="RESET" x="633" y="377" width="100" height="23.3" compId="ID_s4_RESET"/>
		  
			  <subelement type="FEEDBACK" x="59" y="170" width="240" height="180" correctTitleId="ID_s4_CORRECT_TITLE" correctBodyId="ID_s4_CORRECT_BODY" wrongTitleId="ID_s4_INCORRECT_TITLE" wrongBodyId="ID_s4_INCORRECT_BODY"/>
		
		  
		</element>  
	</slide>
	
	</slide>
</data>