<?xml version="1.0" encoding="iso-8859-1"?>
<data>
<slide>
			<element type="IMAGE" src="6_1_2_3.png" x="5" y="33" width="461.3" height="243.7"/>

			<element type="TEXT" subType="TITLE" compId="ID_title" />
			
			<element type="TEXT" compId="ID_txt01" width="61.7" x="58.15" y="176.8" align="center" expand="up+down" />
			
			<element type="TEXT" compId="ID_txt02" width="61.7" x="58.45" y="130.55" align="center" expand="up+down" />
			
			<element type="TEXT" compId="ID_txt03" width="61.7" x="58.15" y="223.05" align="center" expand="up+down" />
			
			<element type="TEXT" compId="ID_txt04" width="61.7" x="341.1" y="129.85" align="center" expand="up+down" />
			
			<element type="TEXT" compId="ID_txt05" width="61.7" x="341.1" y="175.95" align="center" expand="up+down" />		
			
<element type="TEXT" compId="ID_txt07" width="199.95" x="38.3" y="260" align="center" expand="down"  bgColor="#FDE6D4" borderColor="#F68026" corner="5" 
border="2"/>

<element type="TEXT" compId="ID_txt06" width="190" x="266.3" y="260" align="center" expand="down"  bgColor="#FDE6D4" borderColor="#F68026" corner="5" 
border="2"/>

<element type="TEXT" compId="ID_txt08" width="455" x="0" y="350" align="left" expand="up" />	

</slide>

<text id="ID_s1_txt01"><![CDATA[
	<table width="370" border="0" cellspacing="0" cellpadding="0"> <tr> <td>R1(config)#<strong>interface s0/0/0</strong></td> </tr> <tr> <td>R1(config-if)#<strong>ipv6 traffic-filter NO-R3-LAN-ACCESS in</strong></td> </tr></table>
]]></text>


</data>